src/__init__.py
src/config.py
src/data.py
src/embeddings.py
src/ingestion.py
src/llm.py
src/log_handler.py
src/rag.py
src/reranker.py
src/retriever.py
src/utils.py
src/graph/__init__.py
src/graph/consts.py
src/graph/graph.py
src/graph/state.py
src/graph/chains/__init__.py
src/graph/chains/answer_grader.py
src/graph/chains/generation.py
src/graph/chains/hallucination_grader.py
src/graph/chains/retrieval_grader.py
src/graph/chains/router.py
src/graph/nodes/__init__.py
src/graph/nodes/generate.py
src/graph/nodes/grade.py
src/graph/nodes/retrieve.py
src/graph/nodes/web_search.py
src/helpers/__init__.py
src/helpers/create_lib_docs.py
llm_rag-0.1.dist-info/METADATA
llm_rag-0.1.dist-info/WHEEL
llm_rag-0.1.dist-info/top_level.txt
llm_rag-0.1.dist-info/RECORD
