Metadata-Version: 2.2
Name: llm_rag
Version: 0.1
Summary: LLM with RAG
Home-page: https://github.com/mklyazhev/rudn_rag/tree/readme_branch
Author: Vasiliy
Author-email: i@livasan.ru
Classifier: Programming Language :: Python :: 3
Classifier: License :: OSI Approved :: MIT License
Classifier: Operating System :: OS Independent
Requires-Python: >=3.6
Requires-Dist: torch==2.2.1
Requires-Dist: transformers==4.40.2
Requires-Dist: langchain==0.1.16
Requires-Dist: langchain-chroma==0.1.1
Requires-Dist: langchain-openai==0.1.7
Requires-Dist: langchain-community==0.0.34
Requires-Dist: langchain-text-splitters==0.0.2
Requires-Dist: gigachat==0.1.35
Requires-Dist: unstructured[md]==0.11.8
Requires-Dist: sentence-transformers==2.7.0
Requires-Dist: bitsandbytes==0.43.1
Requires-Dist: accelerate==0.30.1
Requires-Dist: xformers==0.0.25
Requires-Dist: aiogram==3.6.0
Requires-Dist: loguru==0.7.2
Requires-Dist: pydantic==2.7.1
Requires-Dist: pydantic-settings==2.2.1
Requires-Dist: setuptools
Dynamic: author
Dynamic: author-email
Dynamic: classifier
Dynamic: description
Dynamic: description-content-type
Dynamic: home-page
Dynamic: requires-dist
Dynamic: requires-python
Dynamic: summary
